libvcs/__about__.py
libvcs/__init__.py
libvcs/exc.py
libvcs/py.typed
libvcs/pytest_plugin.py
libvcs/_internal/__init__.py
libvcs/_internal/dataclasses.py
libvcs/_internal/module_loading.py
libvcs/_internal/query_list.py
libvcs/_internal/run.py
libvcs/_internal/shortcuts.py
libvcs/_internal/subprocess.py
libvcs/_internal/types.py
libvcs/cmd/__init__.py
libvcs/cmd/git.py
libvcs/cmd/hg.py
libvcs/cmd/svn.py
libvcs/data/repotest.dump
libvcs/sync/__init__.py
libvcs/sync/base.py
libvcs/sync/constants.py
libvcs/sync/git.py
libvcs/sync/hg.py
libvcs/sync/svn.py
libvcs/url/__init__.py
libvcs/url/base.py
libvcs/url/constants.py
libvcs/url/git.py
libvcs/url/hg.py
libvcs/url/registry.py
libvcs/url/svn.py
libvcs-0.38.1.dist-info/METADATA
libvcs-0.38.1.dist-info/WHEEL
libvcs-0.38.1.dist-info/entry_points.txt
libvcs-0.38.1.dist-info/licenses/LICENSE
libvcs-0.38.1.dist-info/RECORD
