Metadata-Version: 2.4
Name: libvcs
Version: 0.38.1
Summary: Lite, typed, python utilities for Git, SVN, Mercurial, etc.
Project-URL: Bug Tracker, https://github.com/vcs-python/libvcs/issues
Project-URL: Documentation, https://libvcs.git-pull.com
Project-URL: Repository, https://github.com/vcs-python/libvcs
Project-URL: Changes, https://github.com/vcs-python/libvcs/blob/master/CHANGES
Author-email: Tony Narlock <tony@git-pull.com>
License: MIT
License-File: LICENSE
Keywords: abstraction,checkout,clone,git,hg,lib,library,libvcs,mercurial,scm,subversion,svn,vcs,version control,version-control,wrapper
Classifier: Development Status :: 4 - Beta
Classifier: Environment :: Console
Classifier: Framework :: Pytest
Classifier: Intended Audience :: Developers
Classifier: License :: OSI Approved :: MIT License
Classifier: Operating System :: MacOS :: MacOS X
Classifier: Operating System :: POSIX
Classifier: Programming Language :: Python
Classifier: Programming Language :: Python :: 3
Classifier: Programming Language :: Python :: 3.10
Classifier: Programming Language :: Python :: 3.11
Classifier: Programming Language :: Python :: 3.12
Classifier: Programming Language :: Python :: 3.13
Classifier: Programming Language :: Python :: 3.14
Classifier: Programming Language :: Python :: Implementation :: PyPy
Classifier: Topic :: Software Development :: Libraries :: Python Modules
Classifier: Topic :: Software Development :: Version Control
Classifier: Topic :: Software Development :: Version Control :: Git
Classifier: Topic :: Software Development :: Version Control :: Mercurial
Classifier: Topic :: System :: Shells
Classifier: Topic :: Utilities
Classifier: Typing :: Typed
Requires-Python: <4.0,>=3.10
Requires-Dist: typing-extensions; python_version == '3.10'
